hyde_gopher/__init__.py
hyde_gopher/engine.py
hyde_gopher/generator.py
hyde_gopher/main.py
hyde_gopher/server.py
hyde_gopher/layout_gopher/base.j2
hyde_gopher/layout_gopher/blog.j2
hyde_gopher/layout_gopher/listing.j2
hyde_gopher/layout_gopher/macros.j2
hyde_gopher/layout_gopher/tagged_posts.j2
hyde_gopher-0.4.0.dist-info/LICENSE
hyde_gopher-0.4.0.dist-info/METADATA
hyde_gopher-0.4.0.dist-info/WHEEL
hyde_gopher-0.4.0.dist-info/entry_points.txt
hyde_gopher-0.4.0.dist-info/top_level.txt
hyde_gopher-0.4.0.dist-info/RECORD
