Metadata-Version: 2.1
Name: hyde-gopher
Version: 0.4.0
Summary: a gopher server for Hyde sites
Home-page: https://github.com/YtvwlD/hyde-gopher
Author: Niklas Sombert
Author-email: niklas@ytvwld.de
License: GPLv3
Keywords: hyde,gopher
Platform: UNKNOWN
Classifier: Development Status :: 3 - Alpha
Classifier: Environment :: Console
Classifier: Intended Audience :: Developers
Classifier: Intended Audience :: End Users/Desktop
Classifier: Natural Language :: English
Classifier: Topic :: Utilities
Classifier: Topic :: Internet
Classifier: License :: OSI Approved :: GNU General Public License v3 (GPLv3)
Classifier: Programming Language :: Python :: 3
Classifier: Programming Language :: Python :: 3.6
Classifier: Programming Language :: Python :: 3.7
Classifier: Programming Language :: Python :: 3.8
Classifier: Programming Language :: Python :: 3.9
Requires-Python: ~=3.6
License-File: LICENSE
Requires-Dist: beautifulsoup4
Requires-Dist: commando
Requires-Dist: flask
Requires-Dist: flask-gopher
Requires-Dist: hyde (>=0.9.0)
Requires-Dist: pypandoc
